frame_fixtures/__init__.py
frame_fixtures/core.py
frame_fixtures-1.1.0.dist-info/LICENSE.txt
frame_fixtures-1.1.0.dist-info/METADATA
frame_fixtures-1.1.0.dist-info/WHEEL
frame_fixtures-1.1.0.dist-info/top_level.txt
frame_fixtures-1.1.0.dist-info/RECORD
