Metadata-Version: 2.1
Name: frame-fixtures
Version: 1.1.0
Summary: Use compact expressions to create diverse, deterministic DataFrame fixtures with StaticFrame
Home-page: https://github.com/static-frame/frame-fixtures
Author: Christopher Ariza
License: MIT
Keywords: dataframe fixtures test staticframe pandas numpy
Classifier: Development Status :: 5 - Production/Stable
Classifier: Intended Audience :: Developers
Classifier: Topic :: Software Development
Classifier: Topic :: Scientific/Engineering
Classifier: Topic :: Scientific/Engineering :: Information Analysis
Classifier: License :: OSI Approved :: MIT License
Classifier: Operating System :: MacOS :: MacOS X
Classifier: Operating System :: Microsoft :: Windows
Classifier: Operating System :: POSIX
Classifier: Programming Language :: Python :: 3.9
Classifier: Programming Language :: Python :: 3.10
Classifier: Programming Language :: Python :: 3.11
Classifier: Programming Language :: Python :: 3.12
Requires-Python: >=3.9
License-File: LICENSE.txt
Requires-Dist: numpy >=1.18.5
Provides-Extra: extras
Requires-Dist: static-frame >=1.1.1 ; extra == 'extras'
